booth-multiplier/booth.v
module booth #(parameter OPERAND_BITS = 4) (
        input wire clk,
        input wire [OPERAND_BITS - 1:0] mul1,
        input wire [OPERAND_BITS - 1:0] mul2,
        //input wire [4:0] res_in,
        //output wire [1:0] op,
        //output wire [3:0] val1,
        //output wire [3:0] val2,
        output wire [2 * OPERAND_BITS - 1:0] res_out,
        output reg ready,
        output wire [2 * OPERAND_BITS - 1:0] comp
        );
    localparam N_BITS = $clog2(OPERAND_BITS + 1);
    reg [OPERAND_BITS - 1:0] A;
    reg [OPERAND_BITS - 1:0] Q;
    reg q0;
    reg [OPERAND_BITS - 1:0] M;
    reg [OPERAND_BITS - 1:0] mul2_mem;
    reg [N_BITS - 1:0] n;
    //alu a1 (.clk(clk), .op(op), .val1(val1), .val2(val2), .res(res_in));
    //typedef enum reg [1:0] { LNOP, ADD, SUB, HNOP } operation;
    //operation op1 = SUB; //First action always either shift or subtract
    //assign op = op1;
    assign res_out = {A, Q};
    wire [1:0] op;
    assign op = {Q[0], q0};
    wire [2 * OPERAND_BITS:0] test;
    assign test = {A, Q, q0};
    assign comp = ~(res_out) + 1'b1; //Take 2's comp to get true value
    initial begin
        n <= OPERAND_BITS + 1;
    end
    always @(posedge clk) begin
        if (n == OPERAND_BITS + 1) begin
            A <= 0;
            Q <= mul2;
            q0 <= 1'b0;
            M <= mul1; //Initialize M = mul1
            mul2_mem <= mul2;
        end
        if (ready && ((mul1 != M) || (mul2 != mul2_mem))) begin
            ready = 0;
            n = OPERAND_BITS + 1;
            A <= 0;
            Q <= mul2;
            q0 <= 1'b0;
            M <= mul1;
            mul2_mem <= mul2;
        end
        if (n < OPERAND_BITS + 1 && n != 0) begin
            case(op)
                2'b00: begin 
                    {A, Q, q0} = {A, Q, q0} >> 1;
                    A[OPERAND_BITS - 1] <= A[OPERAND_BITS - 2];
                    end
                2'b01: begin 
                    A = A - M;
                    {A, Q, q0} = {A, Q, q0} >> 1;
                    A[OPERAND_BITS - 1] <= A[OPERAND_BITS - 2];
                    end
                2'b10: begin 
                    A = A + M;
                    {A, Q, q0} = {A, Q, q0} >> 1;
                    A[OPERAND_BITS - 1] <= A[OPERAND_BITS - 2];
                    end
                2'b11: begin 
                    {A, Q, q0} = {A, Q, q0} >> 1;
                    A[OPERAND_BITS - 1] <= A[OPERAND_BITS - 2];
                    end
                default: begin
                    { A, Q, q0 } <= { A, Q, q0 } >> 1;
                    A[OPERAND_BITS - 1] = A[OPERAND_BITS - 2];
                    end
            endcase
        end
        if(n == 1 || n == 0) begin
            ready <= 1;
            n = 0;
        end
        else begin
            ready <= 0;
            n = n - 1;
        end
    end
endmodule

booth-multiplier/tb.v
`timescale 1ns / 1ns
module tb;
    localparam OPERAND_BITS = 4;
    reg clk;
    reg signed [OPERAND_BITS - 1:0] mul1;
    reg signed [OPERAND_BITS - 1:0] mul2;
    wire signed [2 * OPERAND_BITS - 1:0] res_not;
    wire signed [2 * OPERAND_BITS - 1:0] res_true;
    wire ready;
    booth #(.OPERAND_BITS(OPERAND_BITS)) b1(.clk(clk), .mul1(mul1), .mul2(mul2), .res_out(res_not), .ready(ready), .comp(res_true));
    integer i;
    initial begin
        clk = 0;
        for(i = 0; i <= 657918; i = i+1) begin //(OPERAND_BITS + 2) * (2 ** (2 * OPERAND_BITS)) + 2548 ~2^8*10 = (657918 - 2^16) ?
            #5; clk = ~clk;
            #5; clk = ~clk;
        end
    end
    integer j;
    integer k;
    initial begin
        mul1 <= 1;
        mul2 <= 1;
        for(j = 0; j < (2 ** OPERAND_BITS); j = j+1) begin //Iterate all possible combinations
            @(posedge ready) begin
                $display("mul1=%d, mul2=%d, res=%d", mul1, mul2, res_true);
                #15; mul1 <= j;
                for(k = 0; k < (2 ** OPERAND_BITS); k = k+1) begin
                    @(posedge ready) begin
                        $display("mul1=%d, mul2=%d, res=%d", mul1, mul2, res_true);
                        #15; mul2 <= k;
                    end
                end
            end
        end
    end
    initial begin
        $dumpfile("data/dumpfile.vcd");
        $dumpvars(0, tb);
    end
endmodule

booth-multiplier/data/dumpfile.vcd
$date
	Sun Jul 28 01:45:45 2019
$end
$version
	Icarus Verilog
$end
$timescale
	1ns
$end
$scope module tb $end
$var wire 8 ! res_true [7:0] $end
$var wire 8 " res_not [7:0] $end
$var wire 1 # ready $end
$var reg 1 $ clk $end
$var reg 4 % mul1 [3:0] $end
$var reg 4 & mul2 [3:0] $end
$var integer 32 ' i [31:0] $end
$var integer 32 ( j [31:0] $end
$var integer 32 ) k [31:0] $end
$scope module b1 $end
$var wire 1 $ clk $end
$var wire 4 * mul1 [3:0] $end
$var wire 4 + mul2 [3:0] $end
$var wire 9 , test [8:0] $end
$var wire 8 - res_out [7:0] $end
$var wire 2 . op [1:0] $end
$var wire 8 / comp [7:0] $end
$var reg 4 0 A [3:0] $end
$var reg 4 1 M [3:0] $end
$var reg 4 2 Q [3:0] $end
$var reg 4 3 mul2_mem [3:0] $end
$var reg 3 4 n [2:0] $end
$var reg 1 5 q0 $end
$var reg 1 # ready $end
$upscope $end
$upscope $end
$enddefinitions $end
#0
$dumpvars
x5
b101 4
bx 3
bx 2
bx 1
bx 0
bx /
bx .
bx -
bx ,
b1 +
b1 *
bx )
b0 (
b0 '
b1 &
b1 %
0$
x#
bx "
bx !
$end
#5
b11111111 !
b11111111 /
0#
b1 3
b1 1
b10 .
05
b1 2
b1 "
b1 -
b10 ,
b0 0
b100 4
1$
#10
b1 '
0$
#15
b11111000 !
b11111000 /
b11 4
b1000 2
b1 .
15
b1000 "
b1000 -
b10001 ,
b0 0
1$
#20
b10 '
0$
#25
b100 !
b100 /
b10 4
b1100 2
b0 .
05
b11111100 "
b11111100 -
b111111000 ,
b1111 0
1$
#30
b11 '
0$
#35
b10 !
b10 /
b1 4
b1111 0
b11111110 "
b11111110 -
b111111100 ,
b1110 2
1$
#40
b100 '
0$
#45
1#
b1 !
b1 /
b10 .
b0 4
b1111 0
b11111111 "
b11111111 -
b111111110 ,
b1111 2
1$
#50
b101 '
0$
#55
1$
#60
b0 %
b0 *
b110 '
0$
b0 )
#65
b11111111 !
b11111111 /
b0 1
b1 2
b1 "
b1 -
b10 ,
b0 0
b100 4
0#
1$
#70
b111 '
0$
#75
b0 !
b0 /
b11 4
b0 "
b0 -
b0 2
b1 .
b1 ,
15
1$
#80
b1000 '
0$
#85
b10 4
b0 .
b0 ,
05
1$
#90
b1001 '
0$
#95
b1 4
1$
#100
b1010 '
0$
#105
1#
b0 4
1$
#110
b1011 '
0$
#115
1$
#120
b0 &
b0 +
b1100 '
0$
b1 )
#125
b0 3
b100 4
0#
1$
#130
b1101 '
0$
#135
b11 4
1$
#140
b1110 '
0$
#145
b10 4
1$
#150
b1111 '
0$
#155
b1 4
1$
#160
b10000 '
0$
#165
1#
b0 4
1$
#170
b10001 '
0$
#175
1$
#180
b1 &
b1 +
b10010 '
0$
b10 )
#185
b11111111 !
b11111111 /
b10 .
b1 3
b1 "
b1 -
b10 ,
b1 2
b100 4
0#
1$
#190
b10011 '
0$
#195
b0 !
b0 /
b11 4
b0 "
b0 -
b0 2
b1 .
b1 ,
15
1$
#200
b10100 '
0$
#205
b10 4
b0 .
b0 ,
05
1$
#210
b10101 '
0$
#215
b1 4
1$
#220
b10110 '
0$
#225
1#
b0 4
1$
#230
b10111 '
0$
#235
1$
#240
b10 &
b10 +
b11000 '
0$
b11 )
#245
b11111110 !
b11111110 /
b10 3
b10 "
b10 -
b100 ,
b10 2
b100 4
0#
1$
#250
b11001 '
0$
#255
b11111111 !
b11111111 /
b10 .
b11 4
b1 "
b1 -
b10 ,
b1 2
1$
#260
b11010 '
0$
#265
b0 !
b0 /
b10 4
b0 "
b0 -
b0 2
b1 .
b1 ,
15
1$
#270
b11011 '
0$
#275
b1 4
b0 .
b0 ,
05
1$
#280
b11100 '
0$
#285
1#
b0 4
1$
#290
b11101 '
0$
#295
1$
#300
b11 &
b11 +
b11110 '
0$
b100 )
#305
b11111101 !
b11111101 /
b10 .
b11 3
b11 "
b11 -
b110 ,
b11 2
b100 4
0#
1$
#310
b11111 '
0$
#315
b11111111 !
b11111111 /
b11 4
b1 "
b1 -
b1 2
b11 .
b11 ,
15
1$
#320
b100000 '
0$
#325
b0 !
b0 /
b1 .
b10 4
b0 "
b0 -
b1 ,
b0 2
1$
#330
b100001 '
0$
#335
b1 4
b0 .
b0 ,
05
1$
#340
b100010 '
0$
#345
1#
b0 4
1$
#350
b100011 '
0$
#355
1$
#360
b100 &
b100 +
b100100 '
0$
b101 )
#365
b11111100 !
b11111100 /
b100 3
b100 "
b100 -
b1000 ,
b100 2
b100 4
0#
1$
#370
b100101 '
0$
#375
b11111110 !
b11111110 /
b11 4
b10 "
b10 -
b100 ,
b10 2
1$
#380
b100110 '
0$
#385
b11111111 !
b11111111 /
b10 .
b10 4
b1 "
b1 -
b10 ,
b1 2
1$
#390
b100111 '
0$
#395
b0 !
b0 /
b1 4
b0 "
b0 -
b0 2
b1 .
b1 ,
15
1$
#400
b101000 '
0$
#405
1#
b0 4
b0 .
b0 ,
05
1$
#410
b101001 '
0$
#415
1$
#420
b101 &
b101 +
b101010 '
0$
b110 )
#425
b11111011 !
b11111011 /
b10 .
b101 3
b101 "
b101 -
b1010 ,
b101 2
b100 4
0#
1$
#430
b101011 '
0$
#435
b11111110 !
b11111110 /
b11 4
b10 "
b10 -
b10 2
b1 .
b101 ,
15
1$
#440
b101100 '
0$
#445
b11111111 !
b11111111 /
b10 4
b1 "
b1 -
b1 2
b10 .
b10 ,
05
1$
#450
b101101 '
0$
#455
b0 !
b0 /
b1 4
b0 "
b0 -
b0 2
b1 .
b1 ,
15
1$
#460
b101110 '
0$
#465
1#
b0 4
b0 .
b0 ,
05
1$
#470
b101111 '
0$
#475
1$
#480
b110 &
b110 +
b110000 '
0$
b111 )
#485
b11111010 !
b11111010 /
b110 3
b110 "
b110 -
b1100 ,
b110 2
b100 4
0#
1$
#490
b110001 '
0$
#495
b11111101 !
b11111101 /
b10 .
b11 4
b11 "
b11 -
b110 ,
b11 2
1$
#500
b110010 '
0$
#505
b11111111 !
b11111111 /
b10 4
b1 "
b1 -
b1 2
b11 .
b11 ,
15
1$
#510
b110011 '
0$
#515
b0 !
b0 /
b1 .
b1 4
b0 "
b0 -
b1 ,
b0 2
1$
#520
b110100 '
0$
#525
1#
b0 4
b0 .
b0 ,
05
1$
#530
b110101 '
0$
#535
1$
#540
b111 &
b111 +
b110110 '
0$
b1000 )
#545
b11111001 !
b11111001 /
b10 .
b111 3
b111 "
b111 -
b1110 ,
b111 2
b100 4
0#
1$
#550
b110111 '
0$
#555
b11111101 !
b11111101 /
b11 4
b11 "
b11 -
b11 2
b11 .
b111 ,
15
1$
#560
b111000 '
0$
#565
b11111111 !
b11111111 /
b10 4
b1 "
b1 -
b11 ,
b1 2
1$
#570
b111001 '
0$
#575
b0 !
b0 /
b1 .
b1 4
b0 "
b0 -
b1 ,
b0 2
1$
#580
b111010 '
0$
#585
1#
b0 4
b0 .
b0 ,
05
1$
#590
b111011 '
0$
#595
1$
#600
b1000 &
b1000 +
b111100 '
0$
b1001 )
#605
b11111000 !
b11111000 /
b1000 3
b1000 "
b1000 -
b10000 ,
b1000 2
b100 4
0#
1$
#610
b111101 '
0$
#615
b11111100 !
b11111100 /
b11 4
b100 "
b100 -
b1000 ,
b100 2
1$
#620
b111110 '
0$
#625
b11111110 !
b11111110 /
b10 4
b10 "
b10 -
b100 ,
b10 2
1$
#630
b111111 '
0$
#635
b11111111 !
b11111111 /
b10 .
b1 4
b1 "
b1 -
b10 ,
b1 2
1$
#640
b1000000 '
0$
#645
1#
b0 !
b0 /
b0 4
b0 "
b0 -
b0 2
b1 .
b1 ,
15
1$
#650
b1000001 '
0$
#655
1$
#660
b1001 &
b1001 +
b1000010 '
0$
b1010 )
#665
b11110111 !
b11110111 /
b1001 3
b10 .
05
b1001 "
b1001 -
b10010 ,
b1001 2
b100 4
0#
1$
#670
b1000011 '
0$
#675
b11111100 !
b11111100 /
b11 4
b100 "
b100 -
b100 2
b1 .
b1001 ,
15
1$
#680
b1000100 '
0$
#685
b11111110 !
b11111110 /
b10 4
b10 "
b10 -
b10 2
b0 .
b100 ,
05
1$
#690
b1000101 '
0$
#695
b11111111 !
b11111111 /
b10 .
b1 4
b1 "
b1 -
b10 ,
b1 2
1$
#700
b1000110 '
0$
#705
1#
b0 !
b0 /
b0 4
b0 "
b0 -
b0 2
b1 .
b1 ,
15
1$
#710
b1000111 '
0$
#715
1$
#720
b1010 &
b1010 +
b1001000 '
0$
b1011 )
#725
b11110110 !
b11110110 /
b1010 3
b0 .
05
b1010 "
b1010 -
b10100 ,
b1010 2
b100 4
0#
1$
#730
b1001001 '
0$
#735
b11111011 !
b11111011 /
b10 .
b11 4
b101 "
b101 -
b1010 ,
b101 2
1$
#740
b1001010 '
0$
#745
b11111110 !
b11111110 /
b10 4
b10 "
b10 -
b10 2
b1 .
b101 ,
15
1$
#750
b1001011 '
0$
#755
b11111111 !
b11111111 /
b1 4
b1 "
b1 -
b1 2
b10 .
b10 ,
05
1$
#760
b1001100 '
0$
#765
1#
b0 !
b0 /
b0 4
b0 "
b0 -
b0 2
b1 .
b1 ,
15
1$
#770
b1001101 '
0$
#775
1$
#780
b1011 &
b1011 +
b1001110 '
0$
b1100 )
#785
b11110101 !
b11110101 /
b1011 3
b10 .
05
b1011 "
b1011 -
b10110 ,
b1011 2
b100 4
0#
1$
#790
b1001111 '
0$
#795
b11111011 !
b11111011 /
b11 4
b101 "
b101 -
b101 2
b11 .
b1011 ,
15
1$
#800
b1010000 '
0$
#805
b11111110 !
b11111110 /
b1 .
b10 4
b10 "
b10 -
b101 ,
b10 2
1$
#810
b1010001 '
0$
#815
b11111111 !
b11111111 /
b1 4
b1 "
b1 -
b1 2
b10 .
b10 ,
05
1$
#820
b1010010 '
0$
#825
1#
b0 !
b0 /
b0 4
b0 "
b0 -
b0 2
b1 .
b1 ,
15
1$
#830
b1010011 '
0$
#835
1$
#840
b1100 &
b1100 +
b1010100 '
0$
b1101 )
#845
b11110100 !
b11110100 /
b1100 3
b0 .
05
b1100 "
b1100 -
b11000 ,
b1100 2
b100 4
0#
1$
#850
b1010101 '
0$
#855
b11111010 !
b11111010 /
b11 4
b110 "
b110 -
b1100 ,
b110 2
1$
#860
b1010110 '
0$
#865
b11111101 !
b11111101 /
b10 .
b10 4
b11 "
b11 -
b110 ,
b11 2
1$
#870
b1010111 '
0$
#875
b11111111 !
b11111111 /
b1 4
b1 "
b1 -
b1 2
b11 .
b11 ,
15
1$
#880
b1011000 '
0$
#885
1#
b0 !
b0 /
b1 .
b0 4
b0 "
b0 -
b1 ,
b0 2
1$
#890
b1011001 '
0$
#895
1$
#900
b1101 &
b1101 +
b1011010 '
0$
b1110 )
#905
b11110011 !
b11110011 /
b1101 3
b10 .
05
b1101 "
b1101 -
b11010 ,
b1101 2
b100 4
0#
1$
#910
b1011011 '
0$
#915
b11111010 !
b11111010 /
b11 4
b110 "
b110 -
b110 2
b1 .
b1101 ,
15
1$
#920
b1011100 '
0$
#925
b11111101 !
b11111101 /
b10 4
b11 "
b11 -
b11 2
b10 .
b110 ,
05
1$
#930
b1011101 '
0$
#935
b11111111 !
b11111111 /
b1 4
b1 "
b1 -
b1 2
b11 .
b11 ,
15
1$
#940
b1011110 '
0$
#945
1#
b0 !
b0 /
b1 .
b0 4
b0 "
b0 -
b1 ,
b0 2
1$
#950
b1011111 '
0$
#955
1$
#960
b1110 &
b1110 +
b1100000 '
0$
b1111 )
#965
b11110010 !
b11110010 /
b1110 3
b0 .
05
b1110 "
b1110 -
b11100 ,
b1110 2
b100 4
0#
1$
#970
b1100001 '
0$
#975
b11111001 !
b11111001 /
b10 .
b11 4
b111 "
b111 -
b1110 ,
b111 2
1$
#980
b1100010 '
0$
#985
b11111101 !
b11111101 /
b10 4
b11 "
b11 -
b11 2
b11 .
b111 ,
15
1$
#990
b1100011 '
0$
#995
b11111111 !
b11111111 /
b1 4
b1 "
b1 -
b11 ,
b1 2
1$
#1000
b1100100 '
0$
#1005
1#
b0 !
b0 /
b1 .
b0 4
b0 "
b0 -
b1 ,
b0 2
1$
#1010
b1100101 '
0$
#1015
1$
#1020
b1111 &
b1111 +
b1100110 '
0$
b1 (
b10000 )
#1025
b11110001 !
b11110001 /
b1111 3
b10 .
05
b1111 "
b1111 -
b11110 ,
b1111 2
b100 4
0#
1$
#1030
b1100111 '
0$
#1035
b11111001 !
b11111001 /
b11 4
b111 "
b111 -
b111 2
b11 .
b1111 ,
15
1$
#1040
b1101000 '
0$
#1045
b11111101 !
b11111101 /
b10 4
b11 "
b11 -
b111 ,
b11 2
1$
#1050
b1101001 '
0$
#1055
b11111111 !
b11111111 /
b1 4
b1 "
b1 -
b11 ,
b1 2
1$
#1060
b1101010 '
0$
#1065
1#
b0 !
b0 /
b1 .
b0 4
b0 "
b0 -
b1 ,
b0 2
1$
#1070
b1101011 '
0$
#1075
1$
#1080
b1 %
b1 *
b1101100 '
0$
b0 )
#1085
b11110001 !
b11110001 /
b1 1
b10 .
05
b1111 "
b1111 -
b11110 ,
b1111 2
b100 4
0#
1$
#1090
b1101101 '
0$
#1095
b11 4
b11 .
15
b1111 "
b1111 -
b11111 ,
b0 0
1$
#1100
b1101110 '
0$
#1105
b11111001 !
b11111001 /
b10 4
b111 "
b111 -
b1111 ,
b111 2
1$
#1110
b1101111 '
0$
#1115
b11111101 !
b11111101 /
b1 4
b11 "
b11 -
b111 ,
b11 2
1$
#1120
b1110000 '
0$
#1125
1#
b11111111 !
b11111111 /
b0 4
b1 "
b1 -
b11 ,
b1 2
1$
#1130
b1110001 '
0$
#1135
1$
#1140
b0 &
b0 +
b1110010 '
0$
b1 )
#1145
b0 !
b0 /
b0 3
b0 .
05
b0 "
b0 -
b0 ,
b0 2
b100 4
0#
1$
#1150
b1110011 '
0$
#1155
b11 4
1$
#1160
b1110100 '
0$
#1165
b10 4
1$
#1170
b1110101 '
0$
#1175
b1 4
1$
#1180
b1110110 '
0$
#1185
1#
b0 4
1$
#1190
b1110111 '
0$
#1195
1$
#1200
b1 &
b1 +
b1111000 '
0$
b10 )
#1205
b11111111 !
b11111111 /
b10 .
b1 3
b1 "
b1 -
b10 ,
b1 2
b100 4
0#
1$
#1210
b1111001 '
0$
#1215
b11111000 !
b11111000 /
b11 4
b1000 2
b1 .
15
b1000 "
b1000 -
b10001 ,
b0 0
1$
#1220
b1111010 '
0$
#1225
b100 !
b100 /
b10 4
b1100 2
b0 .
05
b11111100 "
b11111100 -
b111111000 ,
b1111 0
1$
#1230
b1111011 '
0$
#1235
b10 !
b10 /
b1 4
b1111 0
b11111110 "
b11111110 -
b111111100 ,
b1110 2
1$
#1240
b1111100 '
0$
#1245
1#
b1 !
b1 /
b10 .
b0 4
b1111 0
b11111111 "
b11111111 -
b111111110 ,
b1111 2
1$
#1250
b1111101 '
0$
#1255
1$
#1260
b10 &
b10 +
b1111110 '
0$
b11 )
#1265
b0 .
b11111110 !
b11111110 /
b10 3
b10 2
b10 "
b10 -
b100 ,
b0 0
b100 4
0#
1$
#1270
b1111111 '
0$
#1275
b11111111 !
b11111111 /
b10 .
b11 4
b1 "
b1 -
b10 ,
b1 2
1$
#1280
b10000000 '
0$
#1285
b11111000 !
b11111000 /
b10 4
b1000 2
b1 .
15
b1000 "
b1000 -
b10001 ,
b0 0
1$
#1290
b10000001 '
0$
#1295
b100 !
b100 /
b1 4
b1100 2
b0 .
05
b11111100 "
b11111100 -
b111111000 ,
b1111 0
1$
#1300
b10000010 '
0$
#1305
1#
b10 !
b10 /
b0 4
b1111 0
b11111110 "
b11111110 -
b111111100 ,
b1110 2
1$
#1310
b10000011 '
0$
#1315
1$
#1320
b11 &
b11 +
b10000100 '
0$
b100 )
#1325
b10 .
b11111101 !
b11111101 /
b11 3
b11 2
b11 "
b11 -
b110 ,
b0 0
b100 4
0#
1$
#1330
b10000101 '
0$
#1335
b11110111 !
b11110111 /
b11 4
b1001 2
b11 .
15
b1001 "
b1001 -
b10011 ,
b0 0
1$
#1340
b10000110 '
0$
#1345
b11111100 !
b11111100 /
b1 .
b10 4
b100 "
b100 -
b1001 ,
b100 2
1$
#1350
b10000111 '
0$
#1355
b110 !
b110 /
b1 4
b1010 2
b0 .
05
b11111010 "
b11111010 -
b111110100 ,
b1111 0
1$
#1360
b10001000 '
0$
#1365
1#
b11 !
b11 /
b10 .
b0 4
b1111 0
b11111101 "
b11111101 -
b111111010 ,
b1101 2
1$
#1370
b10001001 '
0$
#1375
1$
#1380
b100 &
b100 +
b10001010 '
0$
b101 )
#1385
b0 .
b11111100 !
b11111100 /
b100 3
b100 2
b100 "
b100 -
b1000 ,
b0 0
b100 4
0#
1$
#1390
b10001011 '
0$
#1395
b11111110 !
b11111110 /
b11 4
b10 "
b10 -
b100 ,
b10 2
1$
#1400
b10001100 '
0$
#1405
b11111111 !
b11111111 /
b10 .
b10 4
b1 "
b1 -
b10 ,
b1 2
1$
#1410
b10001101 '
0$
#1415
b11111000 !
b11111000 /
b1 4
b1000 2
b1 .
15
b1000 "
b1000 -
b10001 ,
b0 0
1$
#1420
b10001110 '
0$
#1425
1#
b100 !
b100 /
b0 4
b1100 2
b0 .
05
b11111100 "
b11111100 -
b111111000 ,
b1111 0
1$
#1430
b10001111 '
0$
#1435
1$
#1440
b101 &
b101 +
b10010000 '
0$
b110 )
#1445
b10 .
b11111011 !
b11111011 /
b101 3
b101 2
b101 "
b101 -
b1010 ,
b0 0
b100 4
0#
1$
#1450
b10010001 '
0$
#1455
b11110110 !
b11110110 /
b11 4
b1010 2
b1 .
15
b1010 "
b1010 -
b10101 ,
b0 0
1$
#1460
b10010010 '
0$
#1465
b11 !
b11 /
b10 4
b1101 2
b10 .
05
b11111101 "
b11111101 -
b111111010 ,
b1111 0
1$
#1470
b10010011 '
0$
#1475
b11111010 !
b11111010 /
b1 4
b110 2
b1 .
15
b110 "
b110 -
b1101 ,
b0 0
1$
#1480
b10010100 '
0$
#1485
1#
b101 !
b101 /
b0 4
b1011 2
b10 .
05
b11111011 "
b11111011 -
b111110110 ,
b1111 0
1$
#1490
b10010101 '
0$
#1495
1$
#1500
b110 &
b110 +
b10010110 '
0$
b111 )
#1505
b0 .
b11111010 !
b11111010 /
b110 3
b110 2
b110 "
b110 -
b1100 ,
b0 0
b100 4
0#
1$
#1510
b10010111 '
0$
#1515
b11111101 !
b11111101 /
b10 .
b11 4
b11 "
b11 -
b110 ,
b11 2
1$
#1520
b10011000 '
0$
#1525
b11110111 !
b11110111 /
b10 4
b1001 2
b11 .
15
b1001 "
b1001 -
b10011 ,
b0 0
1$
#1530
b10011001 '
0$
#1535
b11111100 !
b11111100 /
b1 .
b1 4
b100 "
b100 -
b1001 ,
b100 2
1$
#1540
b10011010 '
0$
#1545
1#
b110 !
b110 /
b0 4
b1010 2
b0 .
05
b11111010 "
b11111010 -
b111110100 ,
b1111 0
1$
#1550
b10011011 '
0$
#1555
1$
#1560
b111 &
b111 +
b10011100 '
0$
b1000 )
#1565
b10 .
b11111001 !
b11111001 /
b111 3
b111 2
b111 "
b111 -
b1110 ,
b0 0
b100 4
0#
1$
#1570
b10011101 '
0$
#1575
b11110101 !
b11110101 /
b11 4
b1011 2
b11 .
15
b1011 "
b1011 -
b10111 ,
b0 0
1$
#1580
b10011110 '
0$
#1585
b11111011 !
b11111011 /
b10 4
b101 "
b101 -
b1011 ,
b101 2
1$
#1590
b10011111 '
0$
#1595
b11111110 !
b11111110 /
b1 .
b1 4
b10 "
b10 -
b101 ,
b10 2
1$
#1600
b10100000 '
0$
#1605
1#
b111 !
b111 /
b0 4
b1001 2
b10 .
05
b11111001 "
b11111001 -
b111110010 ,
b1111 0
1$
#1610
b10100001 '
0$
#1615
1$
#1620
b1000 &
b1000 +
b10100010 '
0$
b1001 )
#1625
b0 .
b11111000 !
b11111000 /
b1000 3
b1000 2
b1000 "
b1000 -
b10000 ,
b0 0
b100 4
0#
1$
#1630
b10100011 '
0$
#1635
b11111100 !
b11111100 /
b11 4
b100 "
b100 -
b1000 ,
b100 2
1$
#1640
b10100100 '
0$
#1645
b11111110 !
b11111110 /
b10 4
b10 "
b10 -
b100 ,
b10 2
1$
#1650
b10100101 '
0$
#1655
b11111111 !
b11111111 /
b10 .
b1 4
b1 "
b1 -
b10 ,
b1 2
1$
#1660
b10100110 '
0$
#1665
1#
b11111000 !
b11111000 /
b0 4
b1000 2
b1 .
15
b1000 "
b1000 -
b10001 ,
b0 0
1$
#1670
b10100111 '
0$
#1675
1$
#1680
b1001 &
b1001 +
b10101000 '
0$
b1010 )
#1685
b11110111 !
b11110111 /
b1001 3
b10 .
05
b1001 "
b1001 -
b10010 ,
b1001 2
b100 4
0#
1$
#1690
b10101001 '
0$
#1695
b11110100 !
b11110100 /
b11 4
b1100 2
b1 .
15
b1100 "
b1100 -
b11001 ,
b0 0
1$
#1700
b10101010 '
0$
#1705
b10 !
b10 /
b10 4
b1110 2
b0 .
05
b11111110 "
b11111110 -
b111111100 ,
b1111 0
1$
#1710
b10101011 '
0$
#1715
b1 !
b1 /
b10 .
b1 4
b1111 0
b11111111 "
b11111111 -
b111111110 ,
b1111 2
1$
#1720
b10101100 '
0$
#1725
1#
b11111001 !
b11111001 /
b0 4
b111 2
b11 .
15
b111 "
b111 -
b1111 ,
b0 0
1$
#1730
b10101101 '
0$
#1735
1$
#1740
b1010 &
b1010 +
b10101110 '
0$
b1011 )
#1745
b11110110 !
b11110110 /
b1010 3
b0 .
05
b1010 "
b1010 -
b10100 ,
b1010 2
b100 4
0#
1$
#1750
b10101111 '
0$
#1755
b11111011 !
b11111011 /
b10 .
b11 4
b101 "
b101 -
b1010 ,
b101 2
1$
#1760
b10110000 '
0$
#1765
b11110110 !
b11110110 /
b10 4
b1010 2
b1 .
15
b1010 "
b1010 -
b10101 ,
b0 0
1$
#1770
b10110001 '
0$
#1775
b11 !
b11 /
b1 4
b1101 2
b10 .
05
b11111101 "
b11111101 -
b111111010 ,
b1111 0
1$
#1780
b10110010 '
0$
#1785
1#
b11111010 !
b11111010 /
b0 4
b110 2
b1 .
15
b110 "
b110 -
b1101 ,
b0 0
1$
#1790
b10110011 '
0$
#1795
1$
#1800
b1011 &
b1011 +
b10110100 '
0$
b1100 )
#1805
b11110101 !
b11110101 /
b1011 3
b10 .
05
b1011 "
b1011 -
b10110 ,
b1011 2
b100 4
0#
1$
#1810
b10110101 '
0$
#1815
b11110011 !
b11110011 /
b11 4
b1101 2
b11 .
15
b1101 "
b1101 -
b11011 ,
b0 0
1$
#1820
b10110110 '
0$
#1825
b11111010 !
b11111010 /
b1 .
b10 4
b110 "
b110 -
b1101 ,
b110 2
1$
#1830
b10110111 '
0$
#1835
b101 !
b101 /
b1 4
b1011 2
b10 .
05
b11111011 "
b11111011 -
b111110110 ,
b1111 0
1$
#1840
b10111000 '
0$
#1845
1#
b11111011 !
b11111011 /
b0 4
b101 2
b11 .
15
b101 "
b101 -
b1011 ,
b0 0
1$
#1850
b10111001 '
0$
#1855
1$
#1860
b1100 &
b1100 +
b10111010 '
0$
b1101 )
#1865
b11110100 !
b11110100 /
b1100 3
b0 .
05
b1100 "
b1100 -
b11000 ,
b1100 2
b100 4
0#
1$
#1870
b10111011 '
0$
#1875
b11111010 !
b11111010 /
b11 4
b110 "
b110 -
b1100 ,
b110 2
1$
#1880
b10111100 '
0$
#1885
b11111101 !
b11111101 /
b10 .
b10 4
b11 "
b11 -
b110 ,
b11 2
1$
#1890
b10111101 '
0$
#1895
b11110111 !
b11110111 /
b1 4
b1001 2
b11 .
15
b1001 "
b1001 -
b10011 ,
b0 0
1$
#1900
b10111110 '
0$
#1905
1#
b11111100 !
b11111100 /
b1 .
b0 4
b100 "
b100 -
b1001 ,
b100 2
1$
#1910
b10111111 '
0$
#1915
1$
#1920
b1101 &
b1101 +
b11000000 '
0$
b1110 )
#1925
b11110011 !
b11110011 /
b1101 3
b10 .
05
b1101 "
b1101 -
b11010 ,
b1101 2
b100 4
0#
1$
#1930
b11000001 '
0$
#1935
b11110010 !
b11110010 /
b11 4
b1110 2
b1 .
15
b1110 "
b1110 -
b11101 ,
b0 0
1$
#1940
b11000010 '
0$
#1945
b1 !
b1 /
b10 4
b1111 2
b10 .
05
b11111111 "
b11111111 -
b111111110 ,
b1111 0
1$
#1950
b11000011 '
0$
#1955
b11111001 !
b11111001 /
b1 4
b111 2
b11 .
15
b111 "
b111 -
b1111 ,
b0 0
1$
#1960
b11000100 '
0$
#1965
1#
b11111101 !
b11111101 /
b0 4
b11 "
b11 -
b111 ,
b11 2
1$
#1970
b11000101 '
0$
#1975
1$
#1980
b1110 &
b1110 +
b11000110 '
0$
b1111 )
#1985
b11110010 !
b11110010 /
b1110 3
b0 .
05
b1110 "
b1110 -
b11100 ,
b1110 2
b100 4
0#
1$
#1990
b11000111 '
0$
#1995
b11111001 !
b11111001 /
b10 .
b11 4
b111 "
b111 -
b1110 ,
b111 2
1$
#2000
b11001000 '
0$
#2005
b11110101 !
b11110101 /
b10 4
b1011 2
b11 .
15
b1011 "
b1011 -
b10111 ,
b0 0
1$
#2010
b11001001 '
0$
#2015
b11111011 !
b11111011 /
b1 4
b101 "
b101 -
b1011 ,
b101 2
1$
#2020
b11001010 '
0$
#2025
1#
b11111110 !
b11111110 /
b1 .
b0 4
b10 "
b10 -
b101 ,
b10 2
1$
#2030
b11001011 '
0$
#2035
1$
#2040
b1111 &
b1111 +
b11001100 '
0$
b10 (
b10000 )
#2045
b11110001 !
b11110001 /
b1111 3
b10 .
05
b1111 "
b1111 -
b11110 ,
b1111 2
b100 4
0#
1$
#2050
b11001101 '
0$
